XStatic_Dagre-0.6.4.1-nspkg.pth
XStatic_Dagre-0.6.4.1.dist-info/DESCRIPTION.rst
XStatic_Dagre-0.6.4.1.dist-info/METADATA
XStatic_Dagre-0.6.4.1.dist-info/RECORD
XStatic_Dagre-0.6.4.1.dist-info/WHEEL
XStatic_Dagre-0.6.4.1.dist-info/metadata.json
XStatic_Dagre-0.6.4.1.dist-info/namespace_packages.txt
XStatic_Dagre-0.6.4.1.dist-info/top_level.txt
xstatic/pkg/dagre/__init__.py
xstatic/pkg/dagre/data/dagre.core.js
xstatic/pkg/dagre/data/dagre.core.min.js
xstatic/pkg/dagre/data/dagre.js
xstatic/pkg/dagre/data/dagre.min.js
