Metadata-Version: 2.0
Name: XStatic-Dagre
Version: 0.6.4.1
Summary: Dagre 0.6.4 (XStatic packaging standard)
Home-page: https://github.com/dagrejs/dagre
Maintainer: Michal Arbet
Maintainer-email: michal.arbet@ultimum.io
License: (same as Dagre)
Keywords: dagre xstatic
Platform: any
